ashiart/__init__.py
ashiart/cli.py
ashiart/enhanced.py
ashiart/generator.py
test/__init__.py
test/test_cli.py
test/test_enhanced.py
test/test_generator.py
ashiart-0.1.0.dist-info/METADATA
ashiart-0.1.0.dist-info/WHEEL
ashiart-0.1.0.dist-info/entry_points.txt
ashiart-0.1.0.dist-info/top_level.txt
ashiart-0.1.0.dist-info/RECORD
