Metadata-Version: 2.4
Name: ashiart
Version: 0.1.0
Summary: A package for generating ASCII art from images
Author: Faycal Amrouche
Author-email: example@example.com
Keywords: ascii,art,image,converter
Classifier: Development Status :: 4 - Beta
Classifier: Intended Audience :: Developers
Classifier: License :: OSI Approved :: MIT License
Classifier: Programming Language :: Python :: 3
Classifier: Programming Language :: Python :: 3.7
Classifier: Programming Language :: Python :: 3.8
Classifier: Programming Language :: Python :: 3.9
Classifier: Programming Language :: Python :: 3.10
Classifier: Programming Language :: Python :: 3.11
Classifier: Topic :: Multimedia :: Graphics :: Graphics Conversion
Requires-Python: >=3.6
Requires-Dist: pillow>=10.0.0
Requires-Dist: numpy>=1.20.0
Dynamic: author
Dynamic: author-email
Dynamic: keywords
Dynamic: requires-dist
Dynamic: requires-python
Dynamic: summary
